loolclitools/__init__.py
loolclitools/_getpass.py
loolclitools/_input.py
loolclitools/_interactive_console.py
loolclitools/_main.py
loolclitools/_selector.py
loolclitools-1.0.1.dist-info/LICENSE.md
loolclitools-1.0.1.dist-info/METADATA
loolclitools-1.0.1.dist-info/WHEEL
loolclitools-1.0.1.dist-info/top_level.txt
loolclitools-1.0.1.dist-info/RECORD
