Metadata-Version: 2.1
Name: loolclitools
Version: 1.0.1
Summary: This module brings some tools for building CLIs. 
Home-page: https://github.com/txhx38/loolclitools
Author: lool
Author-email: txhx38@gmail.com
License: UNKNOWN
Platform: UNKNOWN
Requires-Python: >= 3.9
License-File: LICENSE.md
